README
setup.py
djangohttpdigest/__init__.py
djangohttpdigest/authentication.py
djangohttpdigest/client.py
djangohttpdigest/decorators.py
djangohttpdigest/digest.py
djangohttpdigest/http.py
djangohttpdigest/models.py
djangohttpdigest.egg-info/PKG-INFO
djangohttpdigest.egg-info/SOURCES.txt
djangohttpdigest.egg-info/dependency_links.txt
djangohttpdigest.egg-info/top_level.txt