Metadata-Version: 1.0
Name: djangohttpdigest
Version: 0.2.3
Summary: Support for HTTP digest in Django web framework
Home-page: http://devel.almad.net/trac/django-http-digest/
Author: Lukas Linhart
Author-email: bugs@almad.net
License: UNKNOWN
Platform: UNKNOWN
Classifier: Development Status :: 4 - Beta
Classifier: Intended Audience :: Developers
Classifier: Framework :: Django
Classifier: License :: OSI Approved :: BSD License
Classifier: Operating System :: OS Independent
Classifier: Programming Language :: Python :: 2.5
Classifier: Programming Language :: Python :: 2.6
Classifier: Programming Language :: Python :: 2.7
Classifier: Topic :: Internet :: WWW/HTTP
Classifier: Topic :: Software Development :: Libraries :: Python Modules
